{
  "id": "elan",
  "nom": "Élan",
  "nom-scientifique": "Alces alces",
  "famille": "Cervidae",
  "sous-famille": "Capreolinae",
  "ordre": "Artiodactyle",
  "repartition": "Régions froides de l’hémisphère Nord : Scandinavie, Europe de l’Est, Russie, Mongolie, Canada et nord des États-Unis.",
  "categorie": "mammals",
  "type": "Mammifère",
  "taille": "2,3 à 3,2 m de long ; jusqu’à 2,3 m au garrot",
  "regime": "Feuilles, jeunes pousses, rameaux, écorces, plantes aquatiques et végétation des marais.",
  "habitat": "Forêts boréales, taïga, marécages, lacs, rivières et zones humides boisées",
  "description": "Le plus grand cervidé actuel, reconnaissable à ses longues pattes, son museau large et tombant, ainsi qu’aux grands bois aplatis portés par les mâles. Il fréquente volontiers les zones humides et peut se nourrir de plantes aquatiques.",
  "photos": [
    {
      "fichier": "images/mammals/20260505_elan.jpg",
      "lieu": "pair daiza"
    }
  ]
}